checkmate/__init__.py
checkmate/__main__.py
checkmate/contrib/__init__.py
checkmate/contrib/plugins/__init__.py
checkmate/contrib/plugins/all/gptanalyzer/__init__.py
checkmate/contrib/plugins/all/gptanalyzer/analyzer.py
checkmate/contrib/plugins/all/gptanalyzer/issues_data.py
checkmate/contrib/plugins/all/gptanalyzer/setup.py
checkmate/contrib/plugins/cve/__init__.py
checkmate/contrib/plugins/cve/text4shell/__init__.py
checkmate/contrib/plugins/cve/text4shell/analyzer.py
checkmate/contrib/plugins/cve/text4shell/issues_data.py
checkmate/contrib/plugins/cve/text4shell/setup.py
checkmate/contrib/plugins/git/__init__.py
checkmate/contrib/plugins/git/models.py
checkmate/contrib/plugins/git/setup.py
checkmate/contrib/plugins/git/commands/__init__.py
checkmate/contrib/plugins/git/commands/analyze.py
checkmate/contrib/plugins/git/commands/base.py
checkmate/contrib/plugins/git/commands/diff.py
checkmate/contrib/plugins/git/commands/init.py
checkmate/contrib/plugins/git/commands/update_stats.py
checkmate/contrib/plugins/git/hooks/__init__.py
checkmate/contrib/plugins/git/hooks/project.py
checkmate/contrib/plugins/git/lib/__init__.py
checkmate/contrib/plugins/git/lib/repository.py
checkmate/contrib/plugins/git/lib/repository_pygit2.py
checkmate/contrib/plugins/golang/__init__.py
checkmate/contrib/plugins/golang/gostaticcheck/__init__.py
checkmate/contrib/plugins/golang/gostaticcheck/analyzer.py
checkmate/contrib/plugins/golang/gostaticcheck/issues_data.py
checkmate/contrib/plugins/golang/gostaticcheck/setup.py
checkmate/contrib/plugins/iac/__init__.py
checkmate/contrib/plugins/iac/kubescape/__init__.py
checkmate/contrib/plugins/iac/kubescape/analyzer.py
checkmate/contrib/plugins/iac/kubescape/issues_data.py
checkmate/contrib/plugins/iac/kubescape/setup.py
checkmate/contrib/plugins/iac/tfsec/__init__.py
checkmate/contrib/plugins/iac/tfsec/analyzer.py
checkmate/contrib/plugins/iac/tfsec/issues_data.py
checkmate/contrib/plugins/iac/tfsec/setup.py
checkmate2-4.0.67.dist-info/LICENSE.txt
checkmate2-4.0.67.dist-info/METADATA
checkmate2-4.0.67.dist-info/WHEEL
checkmate2-4.0.67.dist-info/entry_points.txt
checkmate2-4.0.67.dist-info/top_level.txt
checkmate2-4.0.67.dist-info/RECORD
