Metadata-Version: 2.1
Name: checkmate2
Version: 4.0.67
Summary: A meta-code checker written in Python.
Author: Andreas Dewes
License: AGPL-3.0
Classifier: Intended Audience :: Developers
Classifier: Programming Language :: Python
Classifier: Topic :: Software Development :: Quality Assurance
License-File: LICENSE.txt
Requires-Dist: blitzdb3
Requires-Dist: pyyaml
Requires-Dist: sqlalchemy
